odoo10_addon_account_cutoff_accrual_subscription-10.0.1.0.0.99.dev5-py3.8-nspkg.pth
odoo/addons/account_cutoff_accrual_subscription/README.rst
odoo/addons/account_cutoff_accrual_subscription/__init__.py
odoo/addons/account_cutoff_accrual_subscription/__manifest__.py
odoo/addons/account_cutoff_accrual_subscription/i18n/account_cutoff_accrual_subscription.pot
odoo/addons/account_cutoff_accrual_subscription/models/__init__.py
odoo/addons/account_cutoff_accrual_subscription/models/account_cutoff.py
odoo/addons/account_cutoff_accrual_subscription/models/account_cutoff_accrual_subscription.py
odoo/addons/account_cutoff_accrual_subscription/readme/CONFIGURE.rst
odoo/addons/account_cutoff_accrual_subscription/readme/CONTRIBUTORS.rst
odoo/addons/account_cutoff_accrual_subscription/readme/DESCRIPTION.rst
odoo/addons/account_cutoff_accrual_subscription/security/ir.model.access.csv
odoo/addons/account_cutoff_accrual_subscription/security/ir_rule.xml
odoo/addons/account_cutoff_accrual_subscription/static/description/icon.png
odoo/addons/account_cutoff_accrual_subscription/static/description/index.html
odoo/addons/account_cutoff_accrual_subscription/views/account_cutoff_accrual_subscription.xml
odoo10_addon_account_cutoff_accrual_subscription-10.0.1.0.0.99.dev5.dist-info/METADATA
odoo10_addon_account_cutoff_accrual_subscription-10.0.1.0.0.99.dev5.dist-info/WHEEL
odoo10_addon_account_cutoff_accrual_subscription-10.0.1.0.0.99.dev5.dist-info/namespace_packages.txt
odoo10_addon_account_cutoff_accrual_subscription-10.0.1.0.0.99.dev5.dist-info/top_level.txt
odoo10_addon_account_cutoff_accrual_subscription-10.0.1.0.0.99.dev5.dist-info/RECORD
